spoofbuz/__init__.py
spoofbuz/spoofbuz.py
spoofbuz-1.0.dist-info/LICENSE
spoofbuz-1.0.dist-info/METADATA
spoofbuz-1.0.dist-info/WHEEL
spoofbuz-1.0.dist-info/top_level.txt
spoofbuz-1.0.dist-info/RECORD
