Metadata-Version: 2.1
Name: spoofbuz
Version: 1.0
Summary: A library for spoofing the Qobuz web player
Home-page: UNKNOWN
Author: DashLt
Author-email: UNKNOWN
License: UNKNOWN
Platform: UNKNOWN
Classifier: Programming Language :: Python :: 3
